examples/__init__.py
examples/agent_managements.py
examples/aws.py
examples/extractions.py
examples/extractions_with_aws.py
examples/multple_extractions.py
examples/test.py
examples/upload_files.py
splore_sdk/__init__.py
splore_sdk/sdk.py
splore_sdk/agents/__init__.py
splore_sdk/agents/agents_service.py
splore_sdk/agents/validations.py
splore_sdk/core/__init__.py
splore_sdk/core/api_client.py
splore_sdk/core/compat.py
splore_sdk/core/constants.py
splore_sdk/core/exceptions.py
splore_sdk/core/logger.py
splore_sdk/core/validators.py
splore_sdk/extractions/__init__.py
splore_sdk/extractions/extractions_service.py
splore_sdk/extractions/validations.py
splore_sdk/search/__init__.py
splore_sdk/search/search_service.py
splore_sdk/search/validations.py
splore_sdk/utils/__init__.py
splore_sdk/utils/file_uploader.py
splore_sdk/utils/markdown_converter.py
splore_sdk/utils/misc.py
splore_sdk/utils/decorators/__init__.py
splore_sdk/utils/decorators/poll_with_timeout.py
splore_sdk/utils/decorators/retry_with_backoff.py
tests/__init__.py
tests/test_agents.py
tests/test_capabilities.py
tests/test_extractions.py
tests/test_file_uploader.py
tests/test_markdown_converter.py
tests/test_sdk.py
tests/test_search.py
splore_sdk-0.1.38.dist-info/METADATA
splore_sdk-0.1.38.dist-info/WHEEL
splore_sdk-0.1.38.dist-info/top_level.txt
splore_sdk-0.1.38.dist-info/RECORD
