Metadata-Version: 2.4
Name: splore-sdk
Version: 0.1.38
Summary: Python SDK for Splore
Home-page: https://github.com/splorehq/splore-sdk-py
Author: DilipCoder
Author-email: DilipCoder <dilips.ven@splore.com>
Project-URL: Homepage, https://github.com/splorehq/splore-sdk-py
Project-URL: Documentation, https://github.com/splorehq/splore-sdk-py
Project-URL: Changelog, https://github.com/splorehq/splore-sdk-py/blob/main/CHANGELOG.md
Project-URL: Issues, https://github.com/splorehq/splore-sdk-py/issues
Project-URL: Releases, https://github.com/splorehq/splore-sdk-py/releases
Classifier: Programming Language :: Python :: 3
Classifier: Programming Language :: Python :: 3.7
Classifier: Programming Language :: Python :: 3.8
Classifier: Programming Language :: Python :: 3.9
Classifier: Programming Language :: Python :: 3.10
Classifier: Programming Language :: Python :: 3.11
Classifier: Programming Language :: Python :: 3.12
Classifier: Programming Language :: Python :: 3.13
Classifier: License :: OSI Approved :: MIT License
Classifier: Operating System :: OS Independent
Requires-Python: >=3.7
Requires-Dist: requests>=2.28.0
Requires-Dist: pydantic<2.0.0,>=1.10.8
Requires-Dist: markdown>=3.4.4
Requires-Dist: tuspy>=1.1.0
Provides-Extra: examples
Requires-Dist: boto3>=1.37.30; extra == "examples"
Requires-Dist: python-dotenv>=1.0.0; extra == "examples"
Provides-Extra: test
Requires-Dist: pytest<8.0.0,>=7.0.0; extra == "test"
Requires-Dist: pytest-mock>=3.0.0; extra == "test"
Requires-Dist: flake8>=5.0.0; extra == "test"
Dynamic: author
Dynamic: home-page
Dynamic: requires-python
